{
    "AX": {
        "error": 0.003976292969966318,
        "filter_outliers_dict": {
            "filter_outliers": true,
            "iterations": 1,
            "std_devs": 2
        },
        "fit": "Average",
        "fn": 112,
        "include_baseline_error": false,
        "n": 120,
        "reviewed": true,
        "value": -0.03728591302569839
    },
    "CDD": {
        "error": 2.9637839700031785e-06,
        "filter_outliers_dict": {
            "filter_outliers": true,
            "iterations": 1,
            "std_devs": 10
        },
        "fit": "Average",
        "fn": 120,
        "include_baseline_error": false,
        "n": 120,
        "reviewed": true,
        "value": 7.4172552558593455e-06
    },
    "H1": {
        "error": 0.003344113430052103,
        "filter_outliers_dict": {
            "filter_outliers": true,
            "iterations": 1,
            "std_devs": 2
        },
        "fit": "Average",
        "fn": 113,
        "include_baseline_error": false,
        "n": 120,
        "reviewed": true,
        "value": 0.057996775338372664
    },
    "H2": {
        "error": 0.0029289647901584465,
        "filter_outliers_dict": {
            "filter_outliers": true,
            "iterations": 1,
            "std_devs": 2
        },
        "fit": "average",
        "value": -0.11018109728008585
    },
    "L1": {
        "error": 0.0015556046683851662,
        "filter_outliers_dict": {
            "filter_outliers": true,
            "iterations": 1,
            "std_devs": 2
        },
        "fit": "Average",
        "fn": 116,
        "include_baseline_error": false,
        "n": 120,
        "reviewed": true,
        "value": -0.027485867167405528
    },
    "L2": {
        "error": 0.0035361676512995653,
        "filter_outliers_dict": {
            "filter_outliers": true,
            "iterations": 1,
            "std_devs": 2
        },
        "fit": "Average",
        "fn": 114,
        "include_baseline_error": false,
        "n": 120,
        "reviewed": true,
        "value": -0.01342337367149364
    }
}