{
    "AX": {
        "error": 0.004565538404884805, 
        "filter_outliers_dict": {
            "filter_outliers": true, 
            "iterations": 1, 
            "std_devs": 2
        }, 
        "fit": "Average", 
        "fn": 117, 
        "include_baseline_error": false, 
        "n": 120, 
        "value": 0.13195853951012987
    }, 
    "CDD": {
        "error": 3.187181057977614e-06, 
        "filter_outliers_dict": {
            "filter_outliers": true, 
            "iterations": 1, 
            "std_devs": 10
        }, 
        "fit": "Average", 
        "fn": 120, 
        "include_baseline_error": false, 
        "n": 120, 
        "value": 8.653464465169237e-06
    }, 
    "H1": {
        "error": 0.003557564542521772, 
        "filter_outliers_dict": {
            "filter_outliers": true, 
            "iterations": 1, 
            "std_devs": 2
        }, 
        "fit": "Average", 
        "fn": 117, 
        "include_baseline_error": false, 
        "n": 120, 
        "value": 0.08143917182420628
    }, 
    "H2": {
        "error": 0.002291314677541386, 
        "filter_outliers_dict": {
            "filter_outliers": true, 
            "iterations": 1, 
            "std_devs": 2
        }, 
        "fit": "Average", 
        "fn": 112, 
        "include_baseline_error": false, 
        "n": 120, 
        "value": -0.08975187313210752
    }, 
    "L1": {
        "error": 0.0017656990354825456, 
        "filter_outliers_dict": {
            "filter_outliers": true, 
            "iterations": 1, 
            "std_devs": 2
        }, 
        "fit": "Average", 
        "fn": 115, 
        "include_baseline_error": false, 
        "n": 120, 
        "value": -0.019961743399819723
    }, 
    "L2": {
        "error": 0.004221811455528218, 
        "filter_outliers_dict": {
            "filter_outliers": true, 
            "iterations": 1, 
            "std_devs": 2
        }, 
        "fit": "Average", 
        "fn": 116, 
        "include_baseline_error": false, 
        "n": 120, 
        "value": -0.006386653586904968
    }
}