{
    "AX": {
        "error": 0.004389890297341551, 
        "filter_outliers_dict": {
            "filter_outliers": true, 
            "iterations": 1, 
            "std_devs": 2
        }, 
        "fit": "average", 
        "value": 0.14706082512815058
    }, 
    "CDD": {
        "error": 2.963783965864954e-06, 
        "filter_outliers_dict": {
            "filter_outliers": true, 
            "iterations": 1, 
            "std_devs": 10
        }, 
        "fit": "average", 
        "value": 7.4172552455029e-06
    }, 
    "H1": {
        "error": 0.0035704534775711973, 
        "filter_outliers_dict": {
            "filter_outliers": true, 
            "iterations": 1, 
            "std_devs": 2
        }, 
        "fit": "average", 
        "value": 0.06153974526681438
    }, 
    "H2": {
        "error": 0.00901399255015623, 
        "filter_outliers_dict": {
            "filter_outliers": true, 
            "iterations": 1, 
            "std_devs": 2
        }, 
        "fit": "average", 
        "value": -0.1804003921714239
    }, 
    "L1": {
        "error": 0.0018099906324844297, 
        "filter_outliers_dict": {
            "filter_outliers": true, 
            "iterations": 1, 
            "std_devs": 2
        }, 
        "fit": "average", 
        "value": -0.0307703961846425
    }, 
    "L2": {
        "error": 0.004203526133759496, 
        "filter_outliers_dict": {
            "filter_outliers": true, 
            "iterations": 1, 
            "std_devs": 2
        }, 
        "fit": "average", 
        "value": -0.02326945289524552
    }
}